<annotation>
	<folder>Yeliz-Etiketleme</folder>
	<filename>2.jpg</filename>
	<path>C:\Users\TCYGULMUS\Desktop\Yeliz-Etiketleme\2.jpg</path>
	<source>
		<database>Unknown</database>
	</source>
	<size>
		<width>800</width>
		<height>600</height>
		<depth>3</depth>
	</size>
	<segmented>0</segmented>
	<object>
		<name>Baret</name>
		<pose>Unspecified</pose>
		<truncated>0</truncated>
		<difficult>0</difficult>
		<bndbox>
			<xmin>121</xmin>
			<ymin>132</ymin>
			<xmax>288</xmax>
			<ymax>212</ymax>
		</bndbox>
	</object>
	<object>
		<name>Baret</name>
		<pose>Unspecified</pose>
		<truncated>0</truncated>
		<difficult>0</difficult>
		<bndbox>
			<xmin>323</xmin>
			<ymin>135</ymin>
			<xmax>473</xmax>
			<ymax>205</ymax>
		</bndbox>
	</object>
</annotation>
