<annotation>
	<folder>train</folder>
	<filename>401.jpg</filename>
	<path>C:\Users\TCSALGHRSI\Desktop\object_detection_demo\data\images\train\401.jpg</path>
	<source>
		<database>Unknown</database>
	</source>
	<size>
		<width>800</width>
		<height>600</height>
		<depth>3</depth>
	</size>
	<segmented>0</segmented>
	<object>
		<name>helmet</name>
		<pose>Unspecified</pose>
		<truncated>0</truncated>
		<difficult>0</difficult>
		<bndbox>
			<xmin>120</xmin>
			<ymin>341</ymin>
			<xmax>300</xmax>
			<ymax>488</ymax>
		</bndbox>
	</object>
	<object>
		<name>helmet</name>
		<pose>Unspecified</pose>
		<truncated>0</truncated>
		<difficult>0</difficult>
		<bndbox>
			<xmin>81</xmin>
			<ymin>192</ymin>
			<xmax>216</xmax>
			<ymax>283</ymax>
		</bndbox>
	</object>
</annotation>
