<annotation>
	<folder>Kubra-Etiketleme</folder>
	<filename>691.jpg</filename>
	<path>C:\Users\TCHERYILMAZ\ai\2019_03_workplace_safety\Kubra-Etiketleme\691.jpg</path>
	<source>
		<database>Unknown</database>
	</source>
	<size>
		<width>800</width>
		<height>600</height>
		<depth>3</depth>
	</size>
	<segmented>0</segmented>
	<object>
		<name>Baret</name>
		<pose>Unspecified</pose>
		<truncated>0</truncated>
		<difficult>0</difficult>
		<bndbox>
			<xmin>138</xmin>
			<ymin>155</ymin>
			<xmax>241</xmax>
			<ymax>201</ymax>
		</bndbox>
	</object>
	<object>
		<name>Baret</name>
		<pose>Unspecified</pose>
		<truncated>0</truncated>
		<difficult>0</difficult>
		<bndbox>
			<xmin>557</xmin>
			<ymin>249</ymin>
			<xmax>666</xmax>
			<ymax>300</ymax>
		</bndbox>
	</object>
</annotation>
