<annotation>
	<folder>Kubra-Etiketleme</folder>
	<filename>730.jpg</filename>
	<path>C:\Users\TCHERYILMAZ\ai\2019_03_workplace_safety\Kubra-Etiketleme\730.jpg</path>
	<source>
		<database>Unknown</database>
	</source>
	<size>
		<width>800</width>
		<height>600</height>
		<depth>3</depth>
	</size>
	<segmented>0</segmented>
	<object>
		<name>Baret</name>
		<pose>Unspecified</pose>
		<truncated>0</truncated>
		<difficult>0</difficult>
		<bndbox>
			<xmin>180</xmin>
			<ymin>141</ymin>
			<xmax>607</xmax>
			<ymax>314</ymax>
		</bndbox>
	</object>
	<object>
		<name>Gozluk</name>
		<pose>Unspecified</pose>
		<truncated>0</truncated>
		<difficult>0</difficult>
		<bndbox>
			<xmin>541</xmin>
			<ymin>285</ymin>
			<xmax>633</xmax>
			<ymax>337</ymax>
		</bndbox>
	</object>
</annotation>
